rerun_query-0.6.19.dist-info/METADATA
rerun_query-0.6.19.dist-info/WHEEL
rerun_query-0.6.19.dist-info/licenses/LICENSE.md
requery/py.typed
requery/__init__.py
requery/requery.pyi
requery/requery.cpython-38-x86_64-linux-gnu.so
rerun_query-0.6.19.dist-info/RECORD
