Metadata-Version: 2.3
Name: rerun_query
Version: 0.6.19
Classifier: Development Status :: 3 - Alpha
Classifier: Natural Language :: English
Classifier: Programming Language :: Rust
Classifier: Programming Language :: Python
Classifier: Programming Language :: Python :: 3
Classifier: Programming Language :: Python :: 3.8
Classifier: Programming Language :: Python :: 3.9
Classifier: Programming Language :: Python :: 3.10
Classifier: Programming Language :: Python :: 3.11
Classifier: Programming Language :: Python :: 3.12
Classifier: Programming Language :: Python :: Implementation :: CPython
Classifier: Framework :: Robot Framework :: Library
Classifier: Intended Audience :: Developers
Classifier: Intended Audience :: Science/Research
Classifier: License :: OSI Approved :: Apache Software License
Classifier: Operating System :: OS Independent
Classifier: Topic :: File Formats
Classifier: Topic :: Software Development :: Libraries :: Python Modules
Requires-Dist: numpy >=1.21
Requires-Dist: python-semantic-release >=9.0
Requires-Dist: pre-commit >=2.20, <3.0 ; extra == 'dev'
Provides-Extra: dev
License-File: LICENSE.md
Summary: A Rust-powered Python package for querying rerun data.
Author: Tiwater Team <hi@tiwater.com>
Author-email: Tiwater Team <hi@tiwater.com>
License: Apache-2.0
Requires-Python: >=3.8
Project-URL: GitHub, https://github.com/tiwater/rerun-query
